cryptocurrencyeda/__init__.py
cryptocurrencyeda/avg_daily_return.py
cryptocurrencyeda/daily_growth_rate.py
cryptocurrencyeda/plot_price.py
cryptocurrencyeda/retrieve_data.py
cryptocurrencyeda-0.3.9.dist-info/LICENSE
cryptocurrencyeda-0.3.9.dist-info/WHEEL
cryptocurrencyeda-0.3.9.dist-info/METADATA
cryptocurrencyeda-0.3.9.dist-info/RECORD
