Metadata-Version: 2.1
Name: cryptocurrencyeda
Version: 0.3.9
Summary: A package to analyze historical cryptocurrency prices and performance
License: MIT
Author: Berkay Bulut
Requires-Python: >=3.9,<4.0
Classifier: License :: OSI Approved :: MIT License
Classifier: Programming Language :: Python :: 3
Classifier: Programming Language :: Python :: 3.10
Classifier: Programming Language :: Python :: 3.9
Requires-Dist: DateTime (>=4.3,<5.0)
Requires-Dist: Sphinx (>=4.4.0,<5.0.0)
Requires-Dist: altair (>=4.2.0,<5.0.0)
Requires-Dist: autoapi (>=2.0.1,<3.0.0)
Requires-Dist: myst-nb (>=0.13.1,<0.14.0)
Requires-Dist: pandas (>=1.4.0,<2.0.0)
Requires-Dist: pytest (>=6.2.5,<7.0.0)
Requires-Dist: sphinx-autoapi (>=1.8.4,<2.0.0)
Requires-Dist: sphinx-rtd-theme (>=1.0.0,<2.0.0)
